sqlalchemy_firebird_async/__init__.py
sqlalchemy_firebird_async/compiler.py
sqlalchemy_firebird_async/fdb.py
sqlalchemy_firebird_async/firebird_driver.py
sqlalchemy_firebird_async/firebirdsql.py
sqlalchemy_firebird_async-0.2.1.dist-info/METADATA
sqlalchemy_firebird_async-0.2.1.dist-info/WHEEL
sqlalchemy_firebird_async-0.2.1.dist-info/entry_points.txt
sqlalchemy_firebird_async-0.2.1.dist-info/licenses/LICENSE
sqlalchemy_firebird_async-0.2.1.dist-info/RECORD
