Metadata-Version: 2.4
Name: sqlalchemy-firebird-async
Version: 0.2.1
Summary: Asyncio support for Firebird in SQLAlchemy
Project-URL: Homepage, https://github.com/attid/sqlalchemy-firebird-async
Author-email: Igor Tolstov <attid0@gmail.com>
License: MIT
License-File: LICENSE
Classifier: Development Status :: 4 - Beta
Classifier: Framework :: AsyncIO
Classifier: Intended Audience :: Developers
Classifier: Programming Language :: Python :: 3
Classifier: Topic :: Database
Requires-Dist: greenlet!=0.4.17
Requires-Dist: sqlalchemy-firebird>=2.0.0
Requires-Dist: sqlalchemy>=2.0.0
Provides-Extra: all
Requires-Dist: fdb>=2.0; extra == 'all'
Requires-Dist: firebird-driver>=1.0; extra == 'all'
Requires-Dist: firebirdsql>=1.0; extra == 'all'
Provides-Extra: fdb
Requires-Dist: fdb>=2.0; extra == 'fdb'
Provides-Extra: firebird-driver
Requires-Dist: firebird-driver>=1.0; extra == 'firebird-driver'
Provides-Extra: firebirdsql
Requires-Dist: firebirdsql>=1.0; extra == 'firebirdsql'
Provides-Extra: test
Requires-Dist: pytest-asyncio>=0.21; extra == 'test'
Requires-Dist: pytest>=7.0; extra == 'test'
Requires-Dist: testcontainers>=3.7.0; extra == 'test'
